gentrie/__init__.py
gentrie/exceptions.py
gentrie/nodes.py
gentrie/protocols.py
gentrie/py.typed
gentrie/types.py
gentrie/validation.py
gentrie/trie/__init__.py
gentrie/trie/access.py
gentrie/trie/base.py
gentrie/trie/collection.py
gentrie/trie/mutation.py
gentrie/trie/removal.py
gentrie/trie/storage.py
gentrie/trie/traversal.py
gentrie/trie/trie_mixins.py
gen_tries-0.9.7.dist-info/METADATA
gen_tries-0.9.7.dist-info/WHEEL
gen_tries-0.9.7.dist-info/licenses/LICENSE
gen_tries-0.9.7.dist-info/RECORD
