Metadata-Version: 2.4
Name: gen-tries
Version: 0.9.7
Summary: Generalized trie implementation
Project-URL: Homepage, https://github.com/JerilynFranz/python-gen-tries
Project-URL: Documentation, https://python-gen-tries.readthedocs.io/en/latest/
Project-URL: Repository, https://github.com/JerilynFranz/python-gen-tries.git
Project-URL: Issues, https://github.com/JerilynFranz/python-gen-tries/issues
Project-URL: Changelog, https://github.com/JerilynFranz/python-gen-tries/blob/main/CHANGELOG.md
Author-email: Jerilyn Franz <opensource@snowhare.com>
Maintainer-email: Jerilyn Franz <opensource@snowhare.com>
License: Apache License
License-File: LICENSE
Keywords: trie
Classifier: Development Status :: 2 - Pre-Alpha
Classifier: Intended Audience :: Developers
Classifier: License :: OSI Approved :: Apache Software License
Classifier: Operating System :: OS Independent
Classifier: Programming Language :: Python :: 3.10
Classifier: Programming Language :: Python :: 3.11
Classifier: Programming Language :: Python :: 3.12
Classifier: Programming Language :: Python :: 3.13
Classifier: Topic :: Software Development :: Libraries
Classifier: Topic :: Software Development :: Libraries :: Python Modules
Requires-Python: >=3.10
